nmoscommon/InteractiveServer.py
nmoscommon/__init__.py
nmoscommon/aggregator.py
nmoscommon/facade.py
nmoscommon/flask_cors.py
nmoscommon/httpserver.py
nmoscommon/interfaceController.py
nmoscommon/ipc.py
nmoscommon/json.py
nmoscommon/logger.py
nmoscommon/mdnsbridge.py
nmoscommon/nmoscommonconfig.py
nmoscommon/ptptime.py
nmoscommon/query.py
nmoscommon/timestamp.py
nmoscommon/utils.py
nmoscommon/webSocketClient.py
nmoscommon/webapi.py
nmoscommon/zmqserver.py
nmoscommon/auth/__init__.py
nmoscommon/auth/auth_middleware.py
nmoscommon/auth/claims_validator.py
nmoscommon/auth/nmos_auth.py
nmoscommon/mdns/__init__.py
nmoscommon/mdns/dnsListener.py
nmoscommon/mdns/dnsService.py
nmoscommon/mdns/dnsServiceController.py
nmoscommon/mdns/dnsUtils.py
nmoscommon/mdns/mdnsCallbackHandler.py
nmoscommon/mdns/mdnsEngine.py
nmoscommon/mdns/mdnsExceptions.py
nmoscommon/mdns/mdnsInterface.py
nmoscommon/mdns/mdnsInterfaceController.py
nmoscommon/mdns/mdnsListener.py
nmoscommon/mdns/mdnsRegistration.py
nmoscommon/mdns/mdnsRegistrationController.py
nmoscommon/mdns/mdnsSubscription.py
nmoscommon/mdns/mdnsSubscriptionController.py
nmoscommon/rql/__init__.py
nmoscommon/rql/converters.py
nmoscommon/rql/parser.py
nmoscommon/rql/dateutil/__init__.py
nmoscommon/rql/dateutil/util.py
nmoscommon/rql/query/__init__.py
nmoscommon/rql/query/mongodb.py
nmoscommon-0.20.1.dist-info/LICENSE.md
nmoscommon-0.20.1.dist-info/METADATA
nmoscommon-0.20.1.dist-info/NOTICE.md
nmoscommon-0.20.1.dist-info/WHEEL
nmoscommon-0.20.1.dist-info/top_level.txt
nmoscommon-0.20.1.dist-info/RECORD
