Metadata-Version: 2.1
Name: nmoscommon
Version: 0.20.1
Summary: Common components for the BBC's NMOS implementations
Home-page: https://github.com/bbc/nmos-common
Author: Peter Brightwell
Author-email: peter.brightwell@bbc.co.uk
License: Apache 2
Platform: UNKNOWN
Requires-Dist: gevent (<=1.4.0,>=1.2.2)
Requires-Dist: greenlet (>=0.4.13)
Requires-Dist: gevent-websocket (>=0.9.3)
Requires-Dist: six (>=1.10.0)
Requires-Dist: flask (>=0.10.1)
Requires-Dist: jinja2 (>=2.7.2)
Requires-Dist: werkzeug (<1.0.0,>=0.14.1)
Requires-Dist: itsdangerous (>=0.24)
Requires-Dist: socketio-client (>=0.5.3)
Requires-Dist: flask-sockets (>=0.1)
Requires-Dist: pyzmq (>=15.2.0)
Requires-Dist: pygments (>=1.6)
Requires-Dist: python-dateutil (<2.8.1,>=2.4.2)
Requires-Dist: oauthlib (<3.0.0)
Requires-Dist: requests-oauthlib (<1.2.0)
Requires-Dist: flask-oauthlib (>=0.9.1)
Requires-Dist: ws4py (>=0.3.2)
Requires-Dist: requests (>=2.6)
Requires-Dist: jsonschema (>=2.3.0)
Requires-Dist: netifaces (>=0.10.6)
Requires-Dist: websocket-client (>=0.18.0)
Requires-Dist: ujson (>=1.33)
Requires-Dist: mediatimestamp (<2.0.0,>=1.0.1)
Requires-Dist: mediajson (<2.0.0,>=1.0.0)
Requires-Dist: authlib (<1.0,>=0.13)
Requires-Dist: pyopenssl
Requires-Dist: cryptography
Requires-Dist: dnspython (>=1.12.0)
Requires-Dist: zeroconf (==0.19.1) ; python_version < "3.0"
Requires-Dist: zeroconf-monkey (==0.1.0) ; python_version < "3.0"
Requires-Dist: wsaccel (>=0.6.2) ; python_version < "3.6"
Requires-Dist: zeroconf (<0.25.0,>=0.21.0) ; python_version >= "3.0"
Requires-Dist: zeroconf-monkey (>=0.1.0) ; python_version >= "3.0"
